queue_worker_local/__init__.py
queue_worker_local/queue_worker.py
queue_worker_local-0.0.54.dist-info/METADATA
queue_worker_local-0.0.54.dist-info/WHEEL
queue_worker_local-0.0.54.dist-info/top_level.txt
queue_worker_local-0.0.54.dist-info/RECORD
