Metadata-Version: 2.4
Name: queue-worker-local
Version: 0.0.54
Home-page: https://github.com/circles-zone/queue-worker-local-python-package
Author: Circles
Author-email: info@circlez.ai
Classifier: Programming Language :: Python :: 3
Classifier: Operating System :: OS Independent
Requires-Dist: database-mysql-local>=0.0.116
Requires-Dist: logger-local>=0.0.71
Requires-Dist: queue-local>=0.0.52
Requires-Dist: python-sdk-local>=0.0.148
Requires-Dist: database-infrastructure-local
Dynamic: author
Dynamic: author-email
Dynamic: classifier
Dynamic: description
Dynamic: description-content-type
Dynamic: home-page
Dynamic: requires-dist
